patapsco/__init__.py
patapsco/__version__.py
patapsco/config.py
patapsco/database.py
patapsco/docs.py
patapsco/error.py
patapsco/helpers.py
patapsco/index.py
patapsco/job.py
patapsco/pipeline.py
patapsco/psq_setup.py
patapsco/rerank.py
patapsco/results.py
patapsco/retrieve.py
patapsco/run.py
patapsco/schema.py
patapsco/score.py
patapsco/text.py
patapsco/topics.py
patapsco/bin/__init__.py
patapsco/bin/main.py
patapsco/bin/map.py
patapsco/bin/normalize.py
patapsco/bin/query.py
patapsco/bin/reduce.py
patapsco/resources/jars/psq-1.0-SNAPSHOT.jar
patapsco/resources/qsub/map.sh
patapsco/resources/qsub/reduce.sh
patapsco/resources/sbatch/map.sh
patapsco/resources/sbatch/reduce.sh
patapsco/resources/stopwords/baidu/zho.txt
patapsco/resources/stopwords/lucene/ara.txt
patapsco/resources/stopwords/lucene/eng.txt
patapsco/resources/stopwords/lucene/fas.txt
patapsco/resources/stopwords/lucene/rus.txt
patapsco/resources/stopwords/lucene/zho.txt
patapsco/util/__init__.py
patapsco/util/file.py
patapsco/util/formats.py
patapsco/util/java.py
patapsco/util/normalize.py
patapsco-0.9.7.dist-info/METADATA
patapsco-0.9.7.dist-info/WHEEL
patapsco-0.9.7.dist-info/entry_points.txt
patapsco-0.9.7.dist-info/top_level.txt
patapsco-0.9.7.dist-info/RECORD
