Metadata-Version: 2.1
Name: patapsco
Version: 0.9.7
Summary: Cross Language Information Retrieval pipeline
Home-page: UNKNOWN
License: BSD
Platform: UNKNOWN
Requires-Python: >=3.6.1
Requires-Dist: beautifulsoup4
Requires-Dist: ftfy
Requires-Dist: jieba
Requires-Dist: luqum
Requires-Dist: more-itertools
Requires-Dist: nltk (>=3.6.0)
Requires-Dist: numpy
Requires-Dist: parsivar-scale
Requires-Dist: psutil
Requires-Dist: pydantic (<1.8.0,>=1.7.1)
Requires-Dist: pymorphy2
Requires-Dist: pyserini (>=0.13.0)
Requires-Dist: pytrec-eval
Requires-Dist: pyyaml
Requires-Dist: sacremoses
Requires-Dist: spacy (>=3.0.0)
Requires-Dist: spacy-pkuseg (<0.1.0,>=0.0.27)
Requires-Dist: sqlitedict
Requires-Dist: stanza (>=1.2.1)
Provides-Extra: dev
Requires-Dist: pytest ; extra == 'dev'
Requires-Dist: flake8 ; extra == 'dev'
Requires-Dist: autopep8 ; extra == 'dev'
